ADIC/Sequence detector/SD.v
module seq_dec(x,clk,reset,z);
input x,clk,reset;
output reg z;
parameter s0=0 ,s1=1, s2=2, s3=3;
reg [0:1] PS,NS;
always @(posedge clk or posedge reset)
if(reset)
PS <= s0;
else
PS <=  NS;

always @(PS,x)
case(PS)
s0:begin
z = x? 0:0;
NS = x? s0:s1;
end

s1: begin
z = x? 0:0;
NS = x? s2:s1;
end

s2: begin
z = x? 0:0;
NS = x? s3:s1;
end

s3: begin
z = x? 0:1;
NS = x? s0:s0;
end
endcase
endmodule

ADIC/Sequence detector/SD_test.v
module seq_test;
reg clk,x,reset;
wire z;
seq_dec a1(x,clk,reset,z);
initial begin
$dumpfile ("seq.vcd");
$dumpvars (0,seq_test);
clk = 1'b0; 
reset = 1'b1;
#15 reset = 1'b0;
end
always #5 clk= ~clk;
initial begin
#12 x=0; #10 x=0; #10 x=1; #10 x=1;
#10 x=0; #10 x=1; #10 x=1; #10 x=0;
#10 x=0; #10 x=1; #10 x=1; #10 x=0;
#10 $finish;
end
endmodule

ADIC/Sequence detector/seq.vcd
$date
    Apr 24, 2024  12:14:13
$end
$version
    TOOL:	ncsim(64)	15.20-s086
$end
$timescale
    1 ns
$end

$scope module seq_test $end
$var reg       1 !    clk  $end
$var reg       1 "    x  $end
$var reg       1 #    reset  $end
$var wire      1 $    z  $end

$scope module a1 $end
$var wire      1 %    x  $end
$var wire      1 &    clk  $end
$var wire      1 '    reset  $end
$var reg       1 (    z  $end
$var parameter 32 )    s0  $end
$var parameter 32 *    s1  $end
$var parameter 32 +    s2  $end
$var parameter 32 ,    s3  $end
$var reg       2 -    PS [0:1] $end
$var reg       2 .    NS [0:1] $end
$upscope $end

$upscope $end

$enddefinitions $end
$dumpvars
b11 ,
b10 +
b1 *
b0 )
0!
x"
1#
0$
x%
0&
1'
0(
b0 -
b0x .
$end
#5
1!
1&
#10
0!
0&
#12
0"
0%
b1 .
#15
0#
1!
1&
0'
b1 -
#20
0!
0&
#25
1!
1&
#30
0!
0&
#32
1"
1%
b10 .
#35
1!
1&
b10 -
b11 .
#40
0!
0&
#45
1!
1&
b11 -
b0 .
#50
0!
0&
#52
0"
0%
1(
1$
#55
1!
1&
b0 -
0(
b1 .
0$
#60
0!
0&
#62
1"
1%
b0 .
#65
1!
1&
#70
0!
0&
#75
1!
1&
#80
0!
0&
#82
0"
0%
b1 .
#85
1!
1&
b1 -
#90
0!
0&
#95
1!
1&
#100
0!
0&
#102
1"
1%
b10 .
#105
1!
1&
b10 -
b11 .
#110
0!
0&
#115
1!
1&
b11 -
b0 .
#120
0!
0&
#122
0"
0%
1(
1$
#125
1!
1&
b0 -
0(
b1 .
0$
